Metadata-Version: 2.2
Name: femtoscope
Version: 0.2.2
Summary: Python code for solving nonlinear PDEs from modified gravity models on unbounded domains
Author: Hugo Lévy
License: MIT License
Project-URL: Repository, https://github.com/onera/femtoscope
Classifier: Programming Language :: Python :: 3
Classifier: License :: OSI Approved :: MIT License
Classifier: Operating System :: OS Independent
Requires-Python: >=3.9
License-File: LICENSE
Requires-Dist: colorcet
Requires-Dist: gmsh==4.11.1
Requires-Dist: jax>=0.4.26
Requires-Dist: matplotlib
Requires-Dist: meshio==4.4.6
Requires-Dist: numpy<2
Requires-Dist: pandas
Requires-Dist: pdoc>=14.5.1
Requires-Dist: pyevtk
Requires-Dist: pytest
Requires-Dist: python-mumps; sys_platform != "win32"
Requires-Dist: pyvista
Requires-Dist: sfepy>=2024.3
